tarko_agent_ui/__init__.py
tarko_agent_ui/_static_version.py
tarko_agent_ui/static/index.html
tarko_agent_ui/static/static/font/KaTeX_AMS-Regular.1608a09b.woff
tarko_agent_ui/static/static/font/KaTeX_AMS-Regular.4aafdb68.ttf
tarko_agent_ui/static/static/font/KaTeX_AMS-Regular.a79f1c31.woff2
tarko_agent_ui/static/static/font/KaTeX_Caligraphic-Bold.b6770918.woff
tarko_agent_ui/static/static/font/KaTeX_Caligraphic-Bold.cce5b8ec.ttf
tarko_agent_ui/static/static/font/KaTeX_Caligraphic-Bold.ec17d132.woff2
tarko_agent_ui/static/static/font/KaTeX_Caligraphic-Regular.07ef19e7.ttf
tarko_agent_ui/static/static/font/KaTeX_Caligraphic-Regular.55fac258.woff2
tarko_agent_ui/static/static/font/KaTeX_Caligraphic-Regular.dad44a7f.woff
tarko_agent_ui/static/static/font/KaTeX_Fraktur-Bold.9f256b85.woff
tarko_agent_ui/static/static/font/KaTeX_Fraktur-Bold.b18f59e1.ttf
tarko_agent_ui/static/static/font/KaTeX_Fraktur-Bold.d42a5579.woff2
tarko_agent_ui/static/static/font/KaTeX_Fraktur-Regular.7c187121.woff
tarko_agent_ui/static/static/font/KaTeX_Fraktur-Regular.d3c882a6.woff2
tarko_agent_ui/static/static/font/KaTeX_Fraktur-Regular.ed38e79f.ttf
tarko_agent_ui/static/static/font/KaTeX_Main-Bold.b74a1a8b.ttf
tarko_agent_ui/static/static/font/KaTeX_Main-Bold.c3fb5ac2.woff2
tarko_agent_ui/static/static/font/KaTeX_Main-Bold.d181c465.woff
tarko_agent_ui/static/static/font/KaTeX_Main-BoldItalic.6f2bb1df.woff2
tarko_agent_ui/static/static/font/KaTeX_Main-BoldItalic.70d8b0a5.ttf
tarko_agent_ui/static/static/font/KaTeX_Main-BoldItalic.e3f82f9d.woff
tarko_agent_ui/static/static/font/KaTeX_Main-Italic.47373d1e.ttf
tarko_agent_ui/static/static/font/KaTeX_Main-Italic.8916142b.woff2
tarko_agent_ui/static/static/font/KaTeX_Main-Italic.9024d815.woff
tarko_agent_ui/static/static/font/KaTeX_Main-Regular.0462f03b.woff2
tarko_agent_ui/static/static/font/KaTeX_Main-Regular.7f51fe03.woff
tarko_agent_ui/static/static/font/KaTeX_Main-Regular.b7f8fe9b.ttf
tarko_agent_ui-0.3.5.dist-info/METADATA
tarko_agent_ui-0.3.5.dist-info/WHEEL
tarko_agent_ui-0.3.5.dist-info/top_level.txt
tarko_agent_ui-0.3.5.dist-info/RECORD
