Metadata-Version: 2.4
Name: tarko-agent-ui
Version: 0.3.5
Summary: Python SDK for managing Tarko Agent UI Builder static assets
Author-email: ULIVZ <chenhaoli@bytedance.com>
Project-URL: Homepage, https://github.com/agent-infra/tarko-agent-ui-python
Project-URL: Repository, https://github.com/agent-infra/tarko-agent-ui-python
Project-URL: Bug Tracker, https://github.com/agent-infra/tarko-agent-ui-python/issues
Classifier: Development Status :: 4 - Beta
Classifier: Intended Audience :: Developers
Classifier: License :: OSI Approved :: MIT License
Classifier: Programming Language :: Python :: 3
Classifier: Programming Language :: Python :: 3.8
Classifier: Programming Language :: Python :: 3.9
Classifier: Programming Language :: Python :: 3.10
Classifier: Programming Language :: Python :: 3.11
Classifier: Programming Language :: Python :: 3.12
Classifier: Topic :: Internet :: WWW/HTTP :: HTTP Servers
Classifier: Topic :: Software Development :: Libraries :: Python Modules
Classifier: Topic :: Software Development :: User Interfaces
Classifier: Framework :: FastAPI
Classifier: Framework :: Flask
Classifier: Framework :: Django
Requires-Python: >=3.8
